auth_service_client/__init__.py
auth_service_client/client.py
eev_auth_service_client-0.0.8.dist-info/METADATA
eev_auth_service_client-0.0.8.dist-info/WHEEL
eev_auth_service_client-0.0.8.dist-info/top_level.txt
eev_auth_service_client-0.0.8.dist-info/RECORD
