Metadata-Version: 2.1
Name: eev-auth-service-client
Version: 0.0.8
Summary: Auth service client
Author: EEVend
Author-email: info@eevend.gmail.com
License: UNKNOWN
Platform: UNKNOWN
Requires-Python: >=3.6
Requires-Dist: requests
Requires-Dist: eevend-libs
